planet_cookbook/__init__.py
planet_cookbook/a_builder.py
planet_cookbook/read_reports.py
planet_cookbook-0.0.2.dist-info/METADATA
planet_cookbook-0.0.2.dist-info/WHEEL
planet_cookbook-0.0.2.dist-info/top_level.txt
planet_cookbook-0.0.2.dist-info/RECORD
