Metadata-Version: 2.4
Name: planet_cookbook
Version: 0.0.2
Requires-Dist: numpy
Requires-Dist: astropy>=4
Requires-Dist: numpy
Requires-Dist: scipy
Requires-Dist: pandas
Requires-Dist: seaborn
Requires-Dist: matplotlib
Requires-Dist: rebound
